COPYING
ChangeLog
HISTORY
MANIFEST.in
README
RELEASING
ez_setup.py
kid-env.sh
makefile
run_tests.py
setup.cfg
setup.py
work.sh
bin/kid
bin/kidc
doc/custom.css
doc/default.css
doc/guide.txt
doc/index.txt
doc/language.txt
doc/makefile
doc/notes.txt
examples/basic/README
examples/basic/self.kid
examples/basic/sysinfo.kid
examples/basic/tutorial.kid
examples/basic/tutorial2.kid
examples/cgi/README
examples/cgi/kid_handler.cgi
examples/cgi/sysinfo.kid
kid/__init__.py
kid/codewriter.py
kid/compile.py
kid/compiler.py
kid/et.py
kid/filter.py
kid/format.py
kid/importer.py
kid/namespace.py
kid/parser.py
kid/properties.py
kid/pull.py
kid/release.py
kid/run.py
kid/serialization.py
kid/server.py
kid/template_util.py
kid/util.py
kid.egg-info/PKG-INFO
kid.egg-info/SOURCES.txt
kid.egg-info/dependency_links.txt
kid.egg-info/entry_points.txt
kid.egg-info/top_level.txt
kid/test/__init__.py
kid/test/test_attribute_interpolation.py
kid/test/test_codewriter.py
kid/test/test_comment.py
kid/test/test_compiler.py
kid/test/test_error.py
kid/test/test_extended_layout.py
kid/test/test_extends.py
kid/test/test_format.py
kid/test/test_kid.py
kid/test/test_kid_lang.py
kid/test/test_layout.py
kid/test/test_match.py
kid/test/test_namespace.py
kid/test/test_parser.py
kid/test/test_properties.py
kid/test/test_scope.py
kid/test/test_serialization.py
kid/test/test_serialization_escaping.py
kid/test/test_suffixes.py
kid/test/test_templatepath.py
kid/test/test_unicode.py
kid/test/util.py
misc/upgrade-0.6.py
test/__init__.py
test/basic-test.html.kid
test/blocks.py
test/context.kid
test/include-me.xml
test/layout.kid
test/serialization.kid
test/template-test.html.kid
test/templates.kid
test/test_attribute_interpolation.kid
test/test_attrs.kid
test/test_backward.kid
test/test_comment_pi.kid
test/test_content.kid
test/test_content_interpolation.kid
test/test_content_structure.kid
test/test_def.kid
test/test_encoding.kid
test/test_entities.kid
test/test_extends.kid
test/test_if.kid
test/test_kid_pi.kid
test/test_layout_page.kid
test/test_match.kid
test/test_match_parent.kid
test/test_namespaces.kid
test/test_omit.kid
test/test_repeat.kid
