Metadata-Version: 1.0
Name: kid
Version: 0.9.4
Summary: A simple and pythonic XML template language
Home-page: http://www.kid-templating.org
Author: Ryan Tomayko
Author-email: rtomayko@gmail.com
License: MIT
Download-URL: http://www.kid-templating.org/dist/0.9.4/kid-0.9.4.tar.gz
Keywords: xml template html web
Platform: UNKNOWN
Classifier: Development Status :: 4 - Beta
Classifier: Environment :: Console
Classifier: Environment :: Web Environment
Classifier: Intended Audience :: Developers
Classifier: License :: OSI Approved :: MIT License
Classifier: Operating System :: OS Independent
Classifier: Programming Language :: Python
Classifier: Topic :: Internet :: WWW/HTTP
Classifier: Topic :: Internet :: WWW/HTTP :: Dynamic Content
Classifier: Topic :: Software Development :: Libraries :: Python Modules
Classifier: Topic :: Text Processing :: Markup :: XML
